hydromt_fiat/__init__.py
hydromt_fiat/fiat.py
hydromt_fiat/spatial_joins.py
hydromt_fiat/util.py
hydromt_fiat/validation.py
hydromt_fiat/version.py
hydromt_fiat/api/__init__.py
hydromt_fiat/api/data_types.py
hydromt_fiat/api/dbs_controller.py
hydromt_fiat/api/exposure_vm.py
hydromt_fiat/api/hydromt_fiat_vm.py
hydromt_fiat/api/model_vm.py
hydromt_fiat/api/svi_vm.py
hydromt_fiat/api/utils.py
hydromt_fiat/api/vulnerability_vm.py
hydromt_fiat/data/global_configuration.xlsx
hydromt_fiat/data/hydromt_fiat_catalog_USA.yml
hydromt_fiat/data/hydromt_fiat_catalog_global.yml
hydromt_fiat/data/attribute_linking/NSI_attributes_to_FIAT.json
hydromt_fiat/data/damage_functions/erosion/ft/GL000.csv
hydromt_fiat/data/damage_functions/erosion/inch/GL000.csv
hydromt_fiat/data/damage_functions/erosion/m/GL000.csv
hydromt_fiat/data/damage_functions/flooding/AllDDF_HAZUS.xlsx
hydromt_fiat/data/damage_functions/flooding/Hazus_IWR_curves.csv
hydromt_fiat/data/damage_functions/flooding/JRC_OSM_mapping.csv
hydromt_fiat/data/damage_functions/flooding/JRC_damage_functions.csv
hydromt_fiat/data/damage_functions/flooding/JRC_damage_functions_calculation.xlsx
hydromt_fiat/data/damage_functions/flooding/README_jrc_osm_mapping.txt
hydromt_fiat/data/growth_scenarios/global_gdp(ppp).xlsx
hydromt_fiat/data/growth_scenarios/global_pop.xlsx
hydromt_fiat/data/max_potential_damages/JRC_base_damage_values.csv
hydromt_fiat/data/max_potential_damages/damage_values_fema_hazus-inventory-technical-manual-4.2.3.xlsx
hydromt_fiat/data/max_potential_damages/us_road_damage.csv
hydromt_fiat/data/new_composite_areas/new_development_area_aggregation_test.gpkg
hydromt_fiat/data/new_composite_areas/new_development_area_test.gpkg
hydromt_fiat/data/new_composite_areas/reference_groundHeight_test.cpg
hydromt_fiat/data/new_composite_areas/reference_groundHeight_test.dbf
hydromt_fiat/data/new_composite_areas/reference_groundHeight_test.prj
hydromt_fiat/data/new_composite_areas/reference_groundHeight_test.qix
hydromt_fiat-0.5.9.dist-info/licenses/LICENSE
hydromt_fiat-0.5.9.dist-info/METADATA
hydromt_fiat-0.5.9.dist-info/WHEEL
hydromt_fiat-0.5.9.dist-info/entry_points.txt
hydromt_fiat-0.5.9.dist-info/top_level.txt
hydromt_fiat-0.5.9.dist-info/RECORD
