Metadata-Version: 2.4
Name: hydromt_fiat
Version: 0.5.9
Author-email: Dirk Eilander <dirk.eilander@deltares.nl>, Frederique de Groen <frederique.degroen@deltares.nl>, Mario Fuentes Monjaraz <mario.fuentesmonjaraz@deltares.nl>, Luis Rodriguez Galvez <luis.rodriguez@deltares.nl>, Lieke Meijer <lieke.meijer@deltares.nl>, Sarah Rautenbach <sarah.rautenbach@deltares.nl>
License: GPL-3.0
Project-URL: Documentation, https://deltares.github.io/hydromt_fiat/
Project-URL: Source, https://github.com/Deltares/hydromt_fiat
Classifier: Development Status :: 4 - Beta
Classifier: Intended Audience :: Developers
Classifier: Intended Audience :: Science/Research
Classifier: Topic :: Scientific/Engineering :: Information Analysis
Classifier: Programming Language :: Python :: 3
Requires-Python: >=3.8
License-File: LICENSE
Requires-Dist: hydromt<1.0
Requires-Dist: geopandas
Requires-Dist: geopy
Requires-Dist: numpy
Requires-Dist: openpyxl
Requires-Dist: pandas
Requires-Dist: pyogrio
Requires-Dist: tomli-w
Requires-Dist: tomli
Requires-Dist: xarray
Requires-Dist: pydantic
Requires-Dist: osmnx<3,>=2
Requires-Dist: census
Requires-Dist: us
Requires-Dist: xarray-spatial
Requires-Dist: tqdm
Requires-Dist: pycountry-convert
Requires-Dist: pyarrow
Requires-Dist: dask
Requires-Dist: pint
Provides-Extra: test
Requires-Dist: testpath; extra == "test"
Requires-Dist: responses; extra == "test"
Requires-Dist: pytest>=2.7.3; extra == "test"
Requires-Dist: pytest-cov; extra == "test"
Provides-Extra: doc
Requires-Dist: sphinx; extra == "doc"
Requires-Dist: sphinx_rtd_theme; extra == "doc"
Requires-Dist: ruff==0.6.8; extra == "doc"
Dynamic: license-file
